cosmos/__init__.py
cosmos/cache.py
cosmos/config.py
cosmos/constants.py
cosmos/converter.py
cosmos/dataset.py
cosmos/exceptions.py
cosmos/io.py
cosmos/log.py
cosmos/provider_info.py
cosmos/settings.py
cosmos/telemetry.py
cosmos/versioning.py
cosmos/_utils/__init__.py
cosmos/_utils/importer.py
cosmos/airflow/__init__.py
cosmos/airflow/_override.py
cosmos/airflow/dag.py
cosmos/airflow/graph.py
cosmos/airflow/task_group.py
cosmos/core/__init__.py
cosmos/core/airflow.py
cosmos/core/graph/__init__.py
cosmos/core/graph/entities.py
cosmos/dbt/__init__.py
cosmos/dbt/executable.py
cosmos/dbt/graph.py
cosmos/dbt/project.py
cosmos/dbt/runner.py
cosmos/dbt/selector.py
cosmos/dbt/parser/__init__.py
cosmos/dbt/parser/output.py
cosmos/dbt/parser/project.py
cosmos/hooks/__init__.py
cosmos/hooks/subprocess.py
cosmos/listeners/__init__.py
cosmos/listeners/dag_run_listener.py
cosmos/listeners/task_instance_listener.py
cosmos/operators/__init__.py
cosmos/operators/airflow_async.py
cosmos/operators/aws_ecs.py
cosmos/operators/aws_eks.py
cosmos/operators/azure_container_instance.py
cosmos/operators/base.py
cosmos/operators/docker.py
cosmos/operators/gcp_cloud_run_job.py
cosmos/operators/kubernetes.py
cosmos/operators/lazy_load.py
cosmos/operators/local.py
cosmos/operators/virtualenv.py
cosmos/operators/watcher.py
cosmos/operators/watcher_kubernetes.py
cosmos/operators/_asynchronous/__init__.py
cosmos/operators/_asynchronous/base.py
cosmos/operators/_asynchronous/bigquery.py
cosmos/operators/_asynchronous/databricks.py
cosmos/operators/_watcher/__init__.py
cosmos/operators/_watcher/base.py
cosmos/operators/_watcher/state.py
cosmos/operators/_watcher/triggerer.py
cosmos/plugin/__init__.py
cosmos/plugin/airflow2.py
cosmos/plugin/airflow3.py
cosmos/plugin/snippets.py
cosmos/plugin/storage.py
cosmos/plugin/templates/dbt_docs.html
cosmos/plugin/templates/dbt_docs_not_set_up.html
cosmos/profiles/__init__.py
cosmos/profiles/base.py
cosmos/profiles/athena/__init__.py
astronomer_cosmos-1.13.0.dist-info/METADATA
astronomer_cosmos-1.13.0.dist-info/WHEEL
astronomer_cosmos-1.13.0.dist-info/entry_points.txt
astronomer_cosmos-1.13.0.dist-info/licenses/LICENSE
astronomer_cosmos-1.13.0.dist-info/RECORD
