Metadata-Version: 2.4
Name: astronomer-cosmos
Version: 1.13.0
Summary: Orchestrate your dbt projects in Airflow
Project-URL: Homepage, https://github.com/astronomer/astronomer-cosmos
Project-URL: Documentation, https://astronomer.github.io/astronomer-cosmos
Project-URL: Source code, https://github.com/astronomer/astronomer-cosmos
Author-email: Astronomer <humans@astronomer.io>
License-Expression: Apache-2.0
License-File: LICENSE
Keywords: airflow,apache-airflow,astronomer,dags,dbt
Classifier: Development Status :: 5 - Production/Stable
Classifier: Environment :: Web Environment
Classifier: Framework :: Apache Airflow
Classifier: Framework :: Apache Airflow :: Provider
Classifier: Intended Audience :: Developers
Classifier: License :: OSI Approved :: Apache Software License
Classifier: Operating System :: OS Independent
Classifier: Programming Language :: Python
Classifier: Programming Language :: Python :: 3
Classifier: Programming Language :: Python :: 3.10
Classifier: Programming Language :: Python :: 3.11
Classifier: Programming Language :: Python :: 3.12
Classifier: Programming Language :: Python :: 3.13
Requires-Python: >=3.10
Requires-Dist: aenum
Requires-Dist: apache-airflow>=2.6.0
Requires-Dist: attrs
Requires-Dist: deprecation
Requires-Dist: jinja2>=3.0.0
Requires-Dist: msgpack
Requires-Dist: openlineage-integration-common
Requires-Dist: packaging>=22.0
Requires-Dist: pydantic>=1.10.0
Requires-Dist: virtualenv
Provides-Extra: all
Requires-Dist: airflow-provider-duckdb>=0.2.0; extra == 'all'
Requires-Dist: apache-airflow-providers-amazon[s3fs]>=3.0.0; extra == 'all'
Requires-Dist: apache-airflow-providers-google>=10.17.0; extra == 'all'
Requires-Dist: apache-airflow-providers-microsoft-azure>=8.5.0; extra == 'all'
Requires-Dist: dbt-athena; extra == 'all'
Requires-Dist: dbt-bigquery; extra == 'all'
Requires-Dist: dbt-clickhouse; extra == 'all'
Requires-Dist: dbt-databricks!=1.9.0; extra == 'all'
Requires-Dist: dbt-duckdb; extra == 'all'
Requires-Dist: dbt-exasol; extra == 'all'
Requires-Dist: dbt-mysql; extra == 'all'
Requires-Dist: dbt-oracle; extra == 'all'
Requires-Dist: dbt-postgres; extra == 'all'
Requires-Dist: dbt-redshift; extra == 'all'
Requires-Dist: dbt-snowflake; extra == 'all'
Requires-Dist: dbt-spark; extra == 'all'
Requires-Dist: dbt-sqlserver; extra == 'all'
Requires-Dist: dbt-starrocks; extra == 'all'
Requires-Dist: dbt-teradata; extra == 'all'
Requires-Dist: dbt-vertica; extra == 'all'
Requires-Dist: gcsfs<2025.3.0; extra == 'all'
Requires-Dist: openlineage-airflow; extra == 'all'
Requires-Dist: openlineage-integration-common!=1.15.0; extra == 'all'
Provides-Extra: amazon
Requires-Dist: apache-airflow-providers-amazon[s3fs]>=3.0.0; extra == 'amazon'
Provides-Extra: aws-ecs
Requires-Dist: apache-airflow-providers-amazon>=8.0.0; extra == 'aws-ecs'
Provides-Extra: aws-eks
Requires-Dist: apache-airflow-providers-amazon>=8.0.0; extra == 'aws-eks'
Provides-Extra: azure-container-instance
Requires-Dist: apache-airflow-providers-microsoft-azure>=8.5.0; extra == 'azure-container-instance'
Provides-Extra: dbt-all
Requires-Dist: dbt-athena; extra == 'dbt-all'
Requires-Dist: dbt-bigquery; extra == 'dbt-all'
Requires-Dist: dbt-clickhouse; extra == 'dbt-all'
Requires-Dist: dbt-databricks!=1.9.0; extra == 'dbt-all'
Requires-Dist: dbt-duckdb; extra == 'dbt-all'
Requires-Dist: dbt-exasol; extra == 'dbt-all'
Requires-Dist: dbt-mysql; extra == 'dbt-all'
Requires-Dist: dbt-oracle; extra == 'dbt-all'
Requires-Dist: dbt-postgres; extra == 'dbt-all'
Requires-Dist: dbt-redshift; extra == 'dbt-all'
Requires-Dist: dbt-snowflake; extra == 'dbt-all'
Requires-Dist: dbt-spark; extra == 'dbt-all'
Requires-Dist: dbt-sqlserver; extra == 'dbt-all'
Requires-Dist: dbt-starrocks; extra == 'dbt-all'
Requires-Dist: dbt-teradata; extra == 'dbt-all'
Requires-Dist: dbt-vertica; extra == 'dbt-all'
Provides-Extra: dbt-athena
Requires-Dist: apache-airflow-providers-amazon>=8.0.0; extra == 'dbt-athena'
Requires-Dist: dbt-athena-community; extra == 'dbt-athena'
Provides-Extra: dbt-bigquery
Requires-Dist: dbt-bigquery; extra == 'dbt-bigquery'
Provides-Extra: dbt-clickhouse
Requires-Dist: dbt-clickhouse; extra == 'dbt-clickhouse'
Provides-Extra: dbt-databricks
Requires-Dist: dbt-databricks; extra == 'dbt-databricks'
Provides-Extra: dbt-duckdb
Requires-Dist: airflow-provider-duckdb>=0.2.0; extra == 'dbt-duckdb'
Requires-Dist: dbt-duckdb; extra == 'dbt-duckdb'
Provides-Extra: dbt-exasol
Requires-Dist: dbt-exasol; extra == 'dbt-exasol'
Provides-Extra: dbt-loom
Requires-Dist: dbt-loom; extra == 'dbt-loom'
Provides-Extra: dbt-mysql
Requires-Dist: dbt-mysql; extra == 'dbt-mysql'
Provides-Extra: dbt-oracle
Requires-Dist: dbt-oracle; extra == 'dbt-oracle'
Provides-Extra: dbt-postgres
Requires-Dist: dbt-postgres; extra == 'dbt-postgres'
Provides-Extra: dbt-redshift
Requires-Dist: dbt-redshift; extra == 'dbt-redshift'
Provides-Extra: dbt-snowflake
Requires-Dist: dbt-snowflake; extra == 'dbt-snowflake'
Provides-Extra: dbt-spark
Requires-Dist: dbt-spark; extra == 'dbt-spark'
Provides-Extra: dbt-sqlserver
Requires-Dist: dbt-sqlserver; extra == 'dbt-sqlserver'
Provides-Extra: dbt-starrocks
Requires-Dist: dbt-starrocks; extra == 'dbt-starrocks'
Provides-Extra: dbt-teradata
Requires-Dist: dbt-teradata; extra == 'dbt-teradata'
Provides-Extra: dbt-vertica
Requires-Dist: dbt-vertica<=1.5.4; extra == 'dbt-vertica'
Provides-Extra: docker
Requires-Dist: apache-airflow-providers-docker>=3.5.0; extra == 'docker'
Provides-Extra: docs
Requires-Dist: apache-airflow-providers-cncf-kubernetes>=7.14.0; extra == 'docs'
Requires-Dist: pydata-sphinx-theme; extra == 'docs'
Requires-Dist: sphinx; extra == 'docs'
Requires-Dist: sphinx-autoapi; extra == 'docs'
Requires-Dist: sphinx-autobuild; extra == 'docs'
Provides-Extra: gcp-cloud-run-job
Requires-Dist: apache-airflow-providers-google>=10.11.0; extra == 'gcp-cloud-run-job'
Provides-Extra: google
Requires-Dist: apache-airflow-providers-google>=10.17.0; extra == 'google'
Requires-Dist: gcsfs<2025.3.0; extra == 'google'
Provides-Extra: kubernetes
Requires-Dist: apache-airflow-providers-cncf-kubernetes>=7.14.0; extra == 'kubernetes'
Provides-Extra: microsoft
Requires-Dist: apache-airflow-providers-microsoft-azure>=8.5.0; extra == 'microsoft'
Provides-Extra: openlineage
Requires-Dist: openlineage-airflow; extra == 'openlineage'
Requires-Dist: openlineage-integration-common!=1.15.0; extra == 'openlineage'
